graphmaster/__init__.py
graphmaster-0.0.2.dist-info/DESCRIPTION.rst
graphmaster-0.0.2.dist-info/METADATA
graphmaster-0.0.2.dist-info/pydist.json
graphmaster-0.0.2.dist-info/RECORD
graphmaster-0.0.2.dist-info/top_level.txt
graphmaster-0.0.2.dist-info/WHEEL
