Metadata-Version: 2.0
Name: graphmaster
Version: 0.0.2
Summary: Doesn't do anything yet.
Home-page: https://github.com/stringertheory/graphmaster5000
Author: Mike Stringer
Author-email: mike.stringer@datascopeanalytics.com
License: Copyright (c) 2014 Mike Stringer
